vinagent/__init__.py
vinagent/agent/__init__.py
vinagent/agent/agent.py
vinagent/agent/prebuilt.py
vinagent/examples/deepsearch.md
vinagent/examples/todaytrend.md
vinagent/extension/sql_database/__init__.py
vinagent/extension/sql_database/prompt.py
vinagent/extension/sql_database/tool.py
vinagent/graph/__init__.py
vinagent/graph/branch.py
vinagent/graph/constants.py
vinagent/graph/errors.py
vinagent/graph/function_graph.py
vinagent/graph/graph.py
vinagent/graph/node.py
vinagent/graph/operator.py
vinagent/graph/schema_utils.py
vinagent/graph/state_graph.py
vinagent/graph/types.py
vinagent/logger/logger.py
vinagent/mcp/__init__.py
vinagent/mcp/client.py
vinagent/mcp/connections.py
vinagent/mcp/error_handler.py
vinagent/mcp/examples/math/README.md
vinagent/mcp/examples/math/main.py
vinagent/mcp/examples/weather/README.md
vinagent/mcp/examples/weather/main.py
vinagent/mcp/examples/weather/pyproject.toml
vinagent/mcp/examples/weather/uv.lock
vinagent/mcp/examples/weather/weather.py
vinagent/mcp/prompts.py
vinagent/mcp/resources.py
vinagent/mcp/sessions.py
vinagent/mcp/tools.py
vinagent/memory/__init__.py
vinagent/memory/history.py
vinagent/memory/memory.py
vinagent/mlflow/__init__.py
vinagent/mlflow/autolog.py
vinagent/multi_agent/__init__.py
vinagent/multi_agent/agent_node.py
vinagent/multi_agent/crew.py
vinagent/oauth2/__init__.py
vinagent/oauth2/authen/secret.json
vinagent/oauth2/client.py
vinagent/oauth2/server.py
vinagent/oauth2/user_gen.py
vinagent/register/__init__.py
vinagent/register/initialize.py
vinagent/register/primary_fn.py
vinagent/register/tool.py
vinagent/tools/apology_incorrect_delivery_email.py
vinagent/tools/average_dogs.py
vinagent/tools/computer_tools.py
vinagent/tools/crm_system/apology_incorrect_delivery_email.py
vinagent/tools/deepsearch.py
vinagent/tools/hello.py
vinagent/tools/legal_assistant/extract_entities.py
vinagent/tools/legal_assistant/search_legal_cases.py
vinagent/tools/legal_assistant/summary_legal.py
vinagent-0.0.6.dist-info/LICENSE
vinagent-0.0.6.dist-info/METADATA
vinagent-0.0.6.dist-info/WHEEL
vinagent-0.0.6.dist-info/RECORD
