Metadata-Version: 2.3
Name: vinagent
Version: 0.0.6
Summary: This is an AI Agent library
Author: phamdinhkhanh
Author-email: phamdinhkhanh.tkt53.neu@gmail.com
Requires-Python: >=3.10,<3.14
Classifier: Programming Language :: Python :: 3
Classifier: Programming Language :: Python :: 3.10
Classifier: Programming Language :: Python :: 3.11
Classifier: Programming Language :: Python :: 3.12
Classifier: Programming Language :: Python :: 3.13
Requires-Dist: PyJWT (==2.10.1)
Requires-Dist: arxiv (==2.1.3)
Requires-Dist: aucodb[graph] (==0.1.7)
Requires-Dist: bcrypt (==4.3.0)
Requires-Dist: googlenewsdecoder (==0.1.7)
Requires-Dist: langchain-core (==0.3.68)
Requires-Dist: langchain-groq (==0.3.6)
Requires-Dist: langchain-openai (==0.3.7)
Requires-Dist: langchain-together (==0.3.0)
Requires-Dist: langgraph (==0.4.7)
Requires-Dist: matplotlib (==3.7.1)
Requires-Dist: mcp (==1.9.0)
Requires-Dist: mlflow (==3.1.0)
Requires-Dist: mlflow-skinny (==3.1.0)
Requires-Dist: pandas (==2.2.3)
Requires-Dist: passlib (==1.7.4)
Requires-Dist: plotly (==5.22.0)
Requires-Dist: python-dotenv (==1.0.0)
Requires-Dist: typing_extensions (==4.14.1)
Requires-Dist: yfinance (==0.2.54)
